pygears_tools/.spacemacs
pygears_tools/__init__.py
pygears_tools/default_cpp.py
pygears_tools/install.py
pygears_tools/pkgs.json
pygears_tools/utils.py
pygears_tools/gtkwave/main.diff
pygears_tools/gtkwave/shmidcat.diff
pygears_tools/gtkwave/tcl_commands.diff
pygears_tools/gtkwave/tcl_support_commands.diff
pygears_tools/gtkwave/tcl_support_commands_h.diff
pygears_tools/gtkwave/ttranslate.diff
pygears_tools/gtkwave/vcd_partial.diff
pygears_tools/gtkwave/wavewindow.diff
pygears_tools-0.1.15.dist-info/LICENSE
pygears_tools-0.1.15.dist-info/METADATA
pygears_tools-0.1.15.dist-info/WHEEL
pygears_tools-0.1.15.dist-info/entry_points.txt
pygears_tools-0.1.15.dist-info/top_level.txt
pygears_tools-0.1.15.dist-info/RECORD
