Metadata-Version: 2.1
Name: pygears-tools
Version: 0.1.15
Summary: Helper scripts for installing pygears related tools
Home-page: https://github.com/bogdanvuk/pygears-tools
Author: Bogdan Vukobratovic
Author-email: bogdan.vukobratovic@gmail.com
License: MIT
Platform: UNKNOWN
